iban_validation_py-0.1.26.dist-info/METADATA
iban_validation_py-0.1.26.dist-info/WHEEL
iban_validation_py/__init__.py
iban_validation_py/iban_validation_py.cpython-310-aarch64-linux-gnu.so
iban_validation_py-0.1.26.dist-info/RECORD
